django_html_utils/__init__.py
django_html_utils/apps.py
django_html_utils/py.typed
django_html_utils/tests.py
django_html_utils/static/css/bootstrap.min.css
django_html_utils/static/css/bootstrap.min.css.map
django_html_utils/static/css/brands.min.css
django_html_utils/static/css/django-bootstrap5.css
django_html_utils/static/css/fontawesome.min.css
django_html_utils/static/css/jquery-ui.min.css
django_html_utils/static/css/jquery-ui.structure.min.css
django_html_utils/static/css/jquery-ui.theme.min.css
django_html_utils/static/css/regular.min.css
django_html_utils/static/css/select2.min.css
django_html_utils/static/css/solid.min.css
django_html_utils/static/css/v5-font-face.min.css
django_html_utils/static/css/images/ui-icons_444444_256x240.png
django_html_utils/static/css/images/ui-icons_555555_256x240.png
django_html_utils/static/css/images/ui-icons_777620_256x240.png
django_html_utils/static/css/images/ui-icons_777777_256x240.png
django_html_utils/static/css/images/ui-icons_cc0000_256x240.png
django_html_utils/static/css/images/ui-icons_ffffff_256x240.png
django_html_utils/static/js/bootstrap.bundle.min.js
django_html_utils/static/js/bootstrap.bundle.min.js.map
django_html_utils/static/js/btn-toggle.js
django_html_utils/static/js/jquery-ui.min.js
django_html_utils/static/js/jquery.min.js
django_html_utils/static/js/jquery.min.map
django_html_utils/static/js/select2.min.js
django_html_utils/static/js/i18n/af.js
django_html_utils/static/js/i18n/ar.js
django_html_utils/static/js/i18n/az.js
django_html_utils/static/js/i18n/bg.js
django_html_utils/static/js/i18n/bn.js
django_html_utils/static/js/i18n/bs.js
django_html_utils/static/js/i18n/ca.js
django_html_utils/static/js/i18n/cs.js
django_html_utils/static/js/i18n/da.js
django_html_utils/static/js/i18n/de.js
django_html_utils/static/js/i18n/dsb.js
django_html_utils/static/js/i18n/el.js
django_html_utils/static/js/i18n/en.js
django_html_utils/static/js/i18n/eo.js
django_html_utils/static/js/i18n/es.js
django_html_utils-0.2.12.dist-info/licenses/LICENSE
django_html_utils-0.2.12.dist-info/METADATA
django_html_utils-0.2.12.dist-info/WHEEL
django_html_utils-0.2.12.dist-info/top_level.txt
django_html_utils-0.2.12.dist-info/RECORD
