Metadata-Version: 2.4
Name: django-html-utils
Version: 0.2.12
Summary: HTML utils app for django.
Author-email: "J. Nathanael Philipp" <nathanael@philipp.land>
License-Expression: GPL-3.0-or-later
Project-URL: Homepage, http://github.com/jnphilipp/django-html-utils
Project-URL: Bug Tracker, http://github.com/jnphilipp/django-html-utils/issues
Keywords: django,bootstrap,jquery,jquery-ui,select2,fontawesome
Classifier: Development Status :: 5 - Production/Stable
Classifier: Environment :: Web Environment
Classifier: Intended Audience :: Developers
Classifier: Operating System :: OS Independent
Classifier: Framework :: Django
Classifier: Framework :: Django :: 4.2
Classifier: Framework :: Django :: 5.2
Classifier: Framework :: Django :: 6.0
Classifier: Programming Language :: Python
Classifier: Programming Language :: Python :: 3.10
Classifier: Programming Language :: Python :: 3.11
Classifier: Programming Language :: Python :: 3.12
Classifier: Programming Language :: Python :: 3.13
Classifier: Programming Language :: Python :: 3.14
Classifier: Topic :: Software Development :: Libraries :: Python Modules
Requires-Python: >=3.10
License-File: LICENSE
Dynamic: license-file
